_mcp_mesh/__init__.py
_mcp_mesh/reload.py
_mcp_mesh/reload_runner.py
_mcp_mesh/engine/__init__.py
_mcp_mesh/engine/async_mcp_client.py
_mcp_mesh/engine/base_injector.py
_mcp_mesh/engine/decorator_registry.py
_mcp_mesh/engine/dependency_injector.py
_mcp_mesh/engine/http_wrapper.py
_mcp_mesh/engine/llm_config.py
_mcp_mesh/engine/llm_errors.py
_mcp_mesh/engine/mesh_llm_agent.py
_mcp_mesh/engine/mesh_llm_agent_injector.py
_mcp_mesh/engine/response_parser.py
_mcp_mesh/engine/self_dependency_proxy.py
_mcp_mesh/engine/session_aware_client.py
_mcp_mesh/engine/session_manager.py
_mcp_mesh/engine/signature_analyzer.py
_mcp_mesh/engine/tool_executor.py
_mcp_mesh/engine/tool_schema_builder.py
_mcp_mesh/engine/unified_mcp_proxy.py
_mcp_mesh/engine/provider_handlers/__init__.py
_mcp_mesh/engine/provider_handlers/base_provider_handler.py
_mcp_mesh/engine/provider_handlers/claude_handler.py
_mcp_mesh/engine/provider_handlers/gemini_handler.py
_mcp_mesh/engine/provider_handlers/generic_handler.py
_mcp_mesh/engine/provider_handlers/openai_handler.py
_mcp_mesh/engine/provider_handlers/provider_handler_registry.py
_mcp_mesh/pipeline/__init__.py
_mcp_mesh/pipeline/api_heartbeat/__init__.py
_mcp_mesh/pipeline/api_heartbeat/api_lifespan_integration.py
_mcp_mesh/pipeline/api_heartbeat/rust_api_heartbeat.py
_mcp_mesh/pipeline/api_startup/__init__.py
_mcp_mesh/pipeline/api_startup/api_pipeline.py
_mcp_mesh/pipeline/api_startup/api_server_setup.py
_mcp_mesh/pipeline/api_startup/fastapi_discovery.py
_mcp_mesh/pipeline/api_startup/middleware_integration.py
_mcp_mesh/pipeline/api_startup/route_collection.py
_mcp_mesh/pipeline/api_startup/route_integration.py
_mcp_mesh/pipeline/mcp_heartbeat/__init__.py
_mcp_mesh/pipeline/mcp_heartbeat/rust_heartbeat.py
_mcp_mesh/pipeline/mcp_startup/__init__.py
_mcp_mesh/pipeline/mcp_startup/configuration.py
_mcp_mesh/pipeline/mcp_startup/decorator_collection.py
_mcp_mesh/pipeline/mcp_startup/fastapiserver_setup.py
mcp_mesh-0.8.1.dist-info/METADATA
mcp_mesh-0.8.1.dist-info/WHEEL
mcp_mesh-0.8.1.dist-info/licenses/LICENSE
mcp_mesh-0.8.1.dist-info/RECORD
